marksum/__init__.py
marksum/cli.py
marksum/llm_provider.py
marksum/prompts/__init__.py
marksum/prompts/bullets.txt
marksum/prompts/default.txt
marksum-0.1.4.dist-info/METADATA
marksum-0.1.4.dist-info/WHEEL
marksum-0.1.4.dist-info/entry_points.txt
marksum-0.1.4.dist-info/RECORD
